[
    {
        "service_name": "Microsoft Entra ID",
        "certification_name": "az104",
        "category": "Identity & Access Management",
        "id": "0ba0bca8-3400-4d00-a09a-36bcbdb927d9"
    },
    {
        "service_name": "Azure roles",
        "certification_name": "az104",
        "category": "Identity & Access Management",
        "id": "68e1d155-ba55-4967-8404-7f0fd382b4cd"
    },
    {
        "service_name": "Azure Policy",
        "certification_name": "az104",
        "category": "Governance & Compliance",
        "id": "443d93ca-c3cc-4eee-b21a-a4670a61ed33"
    },
    {
        "service_name": "Azure Advisor",
        "certification_name": "az104",
        "category": "Monitoring & Management",
        "id": "470117ff-b5a0-462d-8ef7-6fa2383e38ba"
    },
    {
        "service_name": "Azure Storage firewalls and virtual networks",
        "certification_name": "az104",
        "category": "Storage & Data",
        "id": "e39d2ea7-be8a-470f-b501-00512aa4adc8"
    },
    {
        "service_name": "Azure Storage Explorer",
        "certification_name": "az104",
        "category": "Tools & Utilities",
        "id": "2aa76f9b-f99f-409e-bad3-621d900850ea"
    },
    {
        "service_name": "AzCopy",
        "certification_name": "az104",
        "category": "Tools & Utilities",
        "id": "74b52c64-dee0-49d3-9bd3-ca438a471c04"
    },
    {
        "service_name": "Azure Files",
        "certification_name": "az104",
        "category": "Storage & Data",
        "id": "203790e6-215f-4e69-965a-90610dc3e0f4"
    },
    {
        "service_name": "Azure Blob Storage",
        "certification_name": "az104",
        "category": "Storage & Data",
        "id": "8820bc51-8ca5-47b0-859c-f6e81dada563"
    },
    {
        "service_name": "Azure Resource Manager (ARM) templates",
        "certification_name": "az104",
        "category": "Development & DevOps",
        "id": "2857d5f9-5dc7-4301-9fb5-5741029f537d"
    },
    {
        "service_name": "Bicep files",
        "certification_name": "az104",
        "category": "Development & DevOps",
        "id": "1aec7048-c59f-4a0c-8e47-bfc3fd4df987"
    },
    {
        "service_name": "Azure Disk Encryption",
        "certification_name": "az104",
        "category": "Security & Networking",
        "id": "12089bc9-2567-436e-b736-819c49b3d94e"
    },
    {
        "service_name": "Azure Virtual Machine Scale Sets",
        "certification_name": "az104",
        "category": "Compute",
        "id": "d6fe6c69-10b6-4d79-85a6-b76c3e5190a0"
    },
    {
        "service_name": "Azure container registry",
        "certification_name": "az104",
        "category": "Containers & Kubernetes",
        "id": "1d1bd3ca-c8f3-4e72-9c3f-261cbdd57053"
    },
    {
        "service_name": "Azure Container Instances",
        "certification_name": "az104",
        "category": "Containers & Kubernetes",
        "id": "62f2e5aa-1f60-4bd4-a20b-d47e1e5dc5e4"
    },
    {
        "service_name": "Azure Container Apps",
        "certification_name": "az104",
        "category": "Containers & Kubernetes",
        "id": "6c10b1e4-5010-46a6-bca2-6e1ebe9c4c98"
    },
    {
        "service_name": "Azure App Service",
        "certification_name": "az104",
        "category": "Web & Mobile",
        "id": "6a54974c-5f00-430c-bf33-98eab16e5d7c"
    },
    {
        "service_name": "Azure virtual networks",
        "certification_name": "az104",
        "category": "Security & Networking",
        "id": "ade4f8e2-994e-47d3-8f43-6a68d46e0f7b"
    },
    {
        "service_name": "Azure Bastion",
        "certification_name": "az104",
        "category": "Security & Networking",
        "id": "6146a759-0607-4696-abde-18db5a09e629"
    },
    {
        "service_name": "Azure DNS",
        "certification_name": "az104",
        "category": "Security & Networking",
        "id": "1d4a1afa-6e55-4793-b4e8-cbe093cf9920"
    },
    {
        "service_name": "Azure Monitor",
        "certification_name": "az104",
        "category": "Monitoring & Management",
        "id": "20fc88de-80f6-4872-9b6b-ab8483a2d548"
    },
    {
        "service_name": "Azure Monitor Insights",
        "certification_name": "az104",
        "category": "Monitoring & Management",
        "id": "e151eade-8861-4029-8bb8-c324e74c9657"
    },
    {
        "service_name": "Azure Network Watcher",
        "certification_name": "az104",
        "category": "Security & Networking",
        "id": "e59e8936-07ec-4d21-b03a-a39e8108c88e"
    },
    {
        "service_name": "Recovery Services vault",
        "certification_name": "az104",
        "category": "Backup & Recovery",
        "id": "ddb0e3b9-5a53-421d-ad65-837aaca20ed6"
    },
    {
        "service_name": "Azure Backup vault",
        "certification_name": "az104",
        "category": "Backup & Recovery",
        "id": "381f64cf-b8c4-4f6b-8579-758b9cca18fa"
    },
    {
        "service_name": "Azure Backup",
        "certification_name": "az104",
        "category": "Backup & Recovery",
        "id": "541f3599-cfc0-4c08-8327-3e48bcb4eb69"
    },
    {
        "service_name": "Azure Site Recovery",
        "certification_name": "az104",
        "category": "Backup & Recovery",
        "id": "8a7cc644-2f93-479f-8e3e-729c83493987"
    },
    {
        "service_name": "Azure SDK",
        "certification_name": "az204",
        "category": "Development & DevOps",
        "id": "6f8a65bb-b0c2-4420-8aa5-386289af452c"
    },
    {
        "service_name": "Azure Container Registry",
        "certification_name": "az204",
        "category": "Containers & Kubernetes",
        "id": "df1de177-d5e2-46ab-87bc-ab0a51af9cb7"
    },
    {
        "service_name": "Azure Container Instance",
        "certification_name": "az204",
        "category": "Containers & Kubernetes",
        "id": "746d4f66-fe3d-41ea-8c3f-2ba58892a07a"
    },
    {
        "service_name": "Azure regions",
        "certification_name": "az900",
        "category": "Fundamentals",
        "id": "c10d2331-ba76-4f71-829f-19ee83e9f73b"
    },
    {
        "service_name": "Logging and monitoring",
        "certification_name": "az305",
        "category": "Monitoring & Management",
        "id": "89cd5ba1-bca8-44d4-9fd7-cdf61dd1ebef"
    },
    {
        "service_name": "Azure Cosmos DB",
        "certification_name": "az104",
        "category": "Storage & Data",
        "id": "1d499490-72f7-4456-a0c5-fa8b52cb861a"
    },
    {
        "service_name": "Azure Logic Apps",
        "certification_name": "az204",
        "category": "Integration & Analytics",
        "id": "16f7078c-4f6b-4279-b16f-77bd19db2747"
    },
    {
        "service_name": "Azure Function Apps",
        "certification_name": "az204",
        "category": "Compute",
        "id": "e4828b33-ddb8-4f55-ae5c-9f454e2b6139"
    },
    {
        "service_name": "Azure DevTest Labs",
        "certification_name": "az204",
        "category": "Development & DevOps",
        "id": "a95a7c75-8e33-4289-a482-bf5302afdb07"
    },
    {
        "service_name": "Azure Resource Groups",
        "certification_name": "az900",
        "category": "Governance & Compliance",
        "id": "6af03176-4304-4182-a1e2-60e2971629dc"
    },
    {
        "service_name": "Azure Subscriptions",
        "certification_name": "az900",
        "category": "Governance & Compliance",
        "id": "c1e09e05-1925-47dd-ac82-f48e3e4b0d5e"
    },
    {
        "service_name": "Azure Active Directory",
        "certification_name": "az900",
        "category": "Identity & Access Management",
        "id": "2fd2d6a1-e851-4bf8-ad7b-93650e2ee931"
    },
    {
        "service_name": "Azure Traffic Manager",
        "certification_name": "az900",
        "category": "Web & Mobile",
        "id": "e2de059e-9ee0-46fa-bf81-e77e05af8407"
    },
    {
        "service_name": "Azure Load Balancer",
        "certification_name": "az900",
        "category": "Security & Networking",
        "id": "ffb95047-1a25-4d27-be51-7e0c6a2f523a"
    },
    {
        "service_name": "Azure Application Gateway",
        "certification_name": "az900",
        "category": "Security & Networking",
        "id": "86526c3f-3970-4f79-b92f-4691211dc57d"
    },
    {
        "service_name": "Azure Key Vault",
        "certification_name": "az900",
        "category": "Security & Networking",
        "id": "628d78a4-d3cf-4605-8993-e7cb704c286b"
    },
    {
        "service_name": "Azure Managed Disks",
        "certification_name": "az900",
        "category": "Storage & Data",
        "id": "268754af-17ed-4d4a-9759-fc5ece0df8c6"
    },
    {
        "service_name": "Azure Blob Storage",
        "certification_name": "az900",
        "category": "Storage & Data",
        "id": "53f8672a-9d07-41a3-ab47-650d98be8ff5"
    },
    {
        "service_name": "Azure Queues",
        "certification_name": "az900",
        "category": "Storage & Data",
        "id": "880b6e88-c396-4514-92d3-0ae496ebc94c"
    },
    {
        "service_name": "Azure Table Storage",
        "certification_name": "az900",
        "category": "Storage & Data",
        "id": "3b00323a-bd8e-4858-8b1a-9b080294dde0"
    },
    {
        "service_name": "Azure Networking",
        "certification_name": "az900",
        "category": "Security & Networking",
        "id": "9841ea7b-449d-406b-8cab-28d5814629dd"
    },
    {
        "service_name": "Azure Migrate",
        "certification_name": "az305",
        "category": "Migration & Modernization",
        "id": "87a62595-0cca-4ea9-ba89-917d3f0dff9f"
    },
    {
        "service_name": "Azure ExpressRoute",
        "certification_name": "az305",
        "category": "Security & Networking",
        "id": "099ad67e-b5e9-44f7-80c0-066cd2babcb6"
    },
    {
        "service_name": "Azure Synapse Analytics",
        "certification_name": "az305",
        "category": "Integration & Analytics",
        "id": "69e556f1-646a-4670-8e78-379c19f9ca60"
    },
    {
        "service_name": "Azure Stream Analytics",
        "certification_name": "az305",
        "category": "Integration & Analytics",
        "id": "66f9bf17-a9c8-4593-9522-d39efa66a01b"
    }
]